envquest/__init__.py
envquest/arguments.py
envquest/recorders.py
envquest/utils.py
envquest/agents/__init__.py
envquest/agents/a2c_agents.py
envquest/agents/common.py
envquest/agents/dqn_agents.py
envquest/agents/generics.py
envquest/agents/pg_agents.py
envquest/agents/ppo_agents.py
envquest/agents/renforce_agents.py
envquest/agents/sarsa_agents.py
envquest/envs/__init__.py
envquest/envs/common.py
envquest/envs/gym.py
envquest/envs/wrappers.py
envquest/functions/__init__.py
envquest/functions/common.py
envquest/functions/policies.py
envquest/functions/q_values.py
envquest/functions/v_values.py
envquest/memories/__init__.py
envquest/memories/common.py
envquest/memories/replay_memories.py
envquest/trainers/__init__.py
envquest/trainers/common.py
envquest/trainers/mc_trainers.py
envquest/trainers/td_trainers.py
envquest-0.0.12.dist-info/LICENSE
envquest-0.0.12.dist-info/METADATA
envquest-0.0.12.dist-info/WHEEL
envquest-0.0.12.dist-info/top_level.txt
envquest-0.0.12.dist-info/RECORD
