Metadata-Version: 2.2
Name: envquest
Version: 0.0.12
Summary: A collection of Reinforcement Learning algorithms to train autonomous agents in different environments.
Author-email: Medric Sonwa <medric49@gmail.com>
Project-URL: Homepage, https://github.com/medric49/envquest
Project-URL: Issues, https://github.com/medric49/envquest/issues
Classifier: Programming Language :: Python :: 3
Classifier: License :: OSI Approved :: MIT License
Classifier: Operating System :: OS Independent
Requires-Python: >=3.8
License-File: LICENSE
Requires-Dist: gymnasium>=1.0.0
Requires-Dist: imageio[ffmpeg,pyav]>=2.35.1
Requires-Dist: opencv-python>=4.10.0.84
Requires-Dist: pillow>=10.4.0
Requires-Dist: torch>=2.5.1
Requires-Dist: tqdm>=4.67.1
Requires-Dist: wandb[media]>=0.19.1
